osc_bsu_backup/__init__.py
osc_bsu_backup/bsu_backup.py
osc_bsu_backup/cli.py
osc_bsu_backup/error.py
osc_bsu_backup/utils.py
osc_bsu_backup-0.0.5.dist-info/LICENSE
osc_bsu_backup-0.0.5.dist-info/METADATA
osc_bsu_backup-0.0.5.dist-info/WHEEL
osc_bsu_backup-0.0.5.dist-info/entry_points.txt
osc_bsu_backup-0.0.5.dist-info/top_level.txt
osc_bsu_backup-0.0.5.dist-info/RECORD
