Metadata-Version: 2.1
Name: osc-bsu-backup
Version: 0.0.5
Summary: Outscale 
Home-page: http://www.outscale.com/
Author: Outscale SAS
Author-email: remi.jouannet@outscale.com
License-File: LICENSE
Requires-Dist: boto3
